aihive_tools/core/__init__.py
aihive_tools/core/base.py
aihive_tools_core-0.0.4.dist-info/METADATA
aihive_tools_core-0.0.4.dist-info/WHEEL
aihive_tools_core-0.0.4.dist-info/top_level.txt
aihive_tools_core-0.0.4.dist-info/RECORD
