Metadata-Version: 2.1
Name: aihive-tools-core
Version: 0.0.4
Summary: AIHive core package
Author-email: Jacob Weiss <jaweiss2305@gmail.com>
Project-URL: homepage, https://github.com/jacobweiss2305/aihive-tools
Project-URL: repository, https://github.com/jacobweiss2305/aihive-tools/tree/main/packages/core
Requires-Python: >=3.7
